text_geo_map/__init__.py
text_geo_map/main.py
text_geo_map/prompts.py
text_geo_map-2025.12.21225445.dist-info/METADATA
text_geo_map-2025.12.21225445.dist-info/WHEEL
text_geo_map-2025.12.21225445.dist-info/top_level.txt
text_geo_map-2025.12.21225445.dist-info/RECORD
