Metadata-Version: 2.4
Name: text-geo-map
Version: 2025.12.21225445
Summary: text-geo-map turns plain text location descriptions into standardized geospatial data for interactive maps.
Author-email: text-geo-map <hi@eugene.plus>
License: MIT
Project-URL: Homepage, https://github.com/chigwell/text-geo-map
Requires-Python: >=3.9
Requires-Dist: langchain-llm7>=0.0.0
Requires-Dist: llmatch-messages>=0.0.0
Requires-Dist: langchain-core>=0.3.0
